.gitignore
LICENSE
README.md
setup.py
wpspin/__init__.py
wpspin/wpspin.py
wpspin.egg-info/PKG-INFO
wpspin.egg-info/SOURCES.txt
wpspin.egg-info/dependency_links.txt
wpspin.egg-info/entry_points.txt
wpspin.egg-info/top_level.txt