Metadata-Version: 2.1
Name: wpspin
Version: 0.2
Summary: WPS PIN generator written in Python 3
Home-page: https://github.com/drygdryg/wpspin
Author: drygdryg
Author-email: drygdryg2014@yandex.com
License: MIT
Download-URL: https://github.com/drygdryg/wpspin/archive/v0.2.zip
Keywords: wireless wifi wpa wps generator pin code
Platform: UNKNOWN
Classifier: License :: OSI Approved :: MIT License
Classifier: Environment :: Console
Classifier: Topic :: Security
Classifier: Topic :: Utilities
Classifier: Operating System :: OS Independent
Classifier: Programming Language :: Python :: 3.4
Classifier: Programming Language :: Python :: 3.5
Classifier: Programming Language :: Python :: 3.6
Classifier: Programming Language :: Python :: 3.7
Classifier: Programming Language :: Python :: 3.8
Requires-Python: >=3.4
